pydynalist/__init__.py
pydynalist/pydynalist.py
pydynalist-0.2.1.dist-info/LICENCE.txt
pydynalist-0.2.1.dist-info/METADATA
pydynalist-0.2.1.dist-info/WHEEL
pydynalist-0.2.1.dist-info/top_level.txt
pydynalist-0.2.1.dist-info/RECORD
