Metadata-Version: 2.1
Name: pydynalist
Version: 0.2.1
Summary: Dynalist api client
Author-email: Roman Smolnyk <poma23324@gmail.com>
Project-URL: Homepage, https://gitlab.com/roman-smolnyk/pydynalist
Keywords: dynalist
Classifier: Programming Language :: Python :: 3
Classifier: License :: OSI Approved :: MIT License
Classifier: Operating System :: OS Independent
Requires-Python: >=3.8
License-File: LICENCE.txt
Requires-Dist: requests
Provides-Extra: async
Requires-Dist: aiohttp ; extra == 'async'
